dinja-0.1.1.dist-info/METADATA
dinja-0.1.1.dist-info/WHEEL
dinja-0.1.1.dist-info/licenses/LICENSE
dinja/__init__.py
dinja-0.1.1.dist-info/RECORD
