Metadata-Version: 2.1
Name: dinja
Version: 0.1.1
Summary: Singleton class that provides decorators to create custom `filters` and `tags` for Jinja templates.
Author-Email: hlop3z <23062270+hlop3z@users.noreply.github.com>
License: MIT
Project-URL: Homepage, https://github.com/hlop3z/dinja/
Requires-Python: >=3.10
